{
  "index": 3,
  "entries": [
    {
      "type": "BIDDER",
      "id": 0,
      "userName": "Bidder1"
    },
    {
      "type": "BIDDER",
      "id": 1,
      "userName": "Josh"
    },
    {
      "type": "BIDDER",
      "id": 2,
      "userName": "Tam"
    },
    {
      "type": "CONTACT_PERSON",
      "id": 3,
      "userName": "Evan",
      "organizationId": 0
    },
        {
      "type": "CONTACT_PERSON",
      "id": 4,
      "userName": "Adam",
      "organizationId": 0
    }
  ]
}